juju_scaleway/__init__.py
juju_scaleway/cli.py
juju_scaleway/client.py
juju_scaleway/commands.py
juju_scaleway/config.py
juju_scaleway/constraints.py
juju_scaleway/env.py
juju_scaleway/exceptions.py
juju_scaleway/ops.py
juju_scaleway/provider.py
juju_scaleway/runner.py
juju_scaleway/ssh.py
juju_scaleway-1.0.3.dist-info/DESCRIPTION.rst
juju_scaleway-1.0.3.dist-info/entry_points.txt
juju_scaleway-1.0.3.dist-info/METADATA
juju_scaleway-1.0.3.dist-info/metadata.json
juju_scaleway-1.0.3.dist-info/pbr.json
juju_scaleway-1.0.3.dist-info/RECORD
juju_scaleway-1.0.3.dist-info/top_level.txt
juju_scaleway-1.0.3.dist-info/WHEEL
