Metadata-Version: 2.0
Name: juju-scaleway
Version: 1.0.3
Summary: Scaleway integration with juju
Home-page: https://pypi.python.org/pypi/juju-scaleway
Author: Scaleway
Author-email: opensource@scaleway.com
License: BSD
Platform: UNKNOWN
Classifier: Development Status :: 5 - Production/Stable
Classifier: Environment :: Web Environment
Classifier: Intended Audience :: Developers
Classifier: License :: OSI Approved :: BSD License
Classifier: Operating System :: OS Independent
Classifier: Programming Language :: Python
Classifier: Programming Language :: Python :: 2
Classifier: Programming Language :: Python :: 2.7
Classifier: Topic :: Software Development :: Libraries :: Python Modules
Classifier: Topic :: Internet
Classifier: Topic :: System :: Distributed Computing
Requires-Dist: PyYAML
Requires-Dist: requests
Requires-Dist: ndg-httpsclient (>=0.3.3)
Provides-Extra: dev
Requires-Dist: PyYAML; extra == 'dev'
Requires-Dist: requests; extra == 'dev'
Requires-Dist: nose; extra == 'dev'
Requires-Dist: mock; extra == 'dev'
